{
  "containerEnv": {
    "XDEBUG_MODE": "coverage,debug,develop"
  },
  "customizations": {
    "vscode": {
      "extensions": [
        "bmewburn.vscode-intelephense-client",
        "DavidAnson.vscode-markdownlint",
        "dbaeumer.vscode-eslint",
        "donjayamanne.githistory",
        "MehediDracula.php-namespace-resolver",
        "mhutchie.git-graph",
        "recca0120.vscode-phpunit",
        "xdebug.php-debug",
        "wongjn.php-sniffer"
      ],
      "settings": {
        "terminal.integrated.defaultProfile.linux": "zsh"
      }
    }
  },
  "features": {
    "ghcr.io/devcontainers/features/git:1": {},
    "ghcr.io/gvatsal60/dev-container-features/pre-commit:1": {}
  },
  "forwardPorts": [
    9003
  ],
  "image": "mcr.microsoft.com/devcontainers/php:8.4-bookworm",
  "name": "PHP 8.4",
  "portsAttributes": {
    "9003": {
      "label": "Xdebug",
      "onAutoForward": "notify"
    }
  },
  "remoteUser": "vscode"
}
